<?xml version="1.0" encoding="UTF-8"?>
<objects serializationModel="Studio.01.10.00">
    <object class="AudioFile" id="{90749e7b-6c1a-4693-b4e2-7d00da17dabe}">
        <property name="assetPath">
            <value>FasterThanTheEyes_Logic_MWALL_16_48_Footstep_Mud_001.wav</value>
        </property>
        <property name="frequencyInKHz">
            <value>48</value>
        </property>
        <property name="channelCount">
            <value>2</value>
        </property>
        <property name="length">
            <value>0.72760416666666672</value>
        </property>
        <relationship name="masterAssetFolder">
            <destination>{e53f00c9-e5bf-40ca-b2c0-1c36d8db4bd1}</destination>
        </relationship>
    </object>
</objects>
